aifoundry/__init__.py
aifoundry/core.py
aifoundry/compliance/__init__.py
aifoundry/compliance/pii_detector.py
aifoundry/connectors/__init__.py
aifoundry/eval/__init__.py
aifoundry/eval/harness.py
aifoundry/rag/__init__.py
aifoundry/rag/optimizer.py
aifoundry-0.1.0.dist-info/METADATA
aifoundry-0.1.0.dist-info/WHEEL
aifoundry-0.1.0.dist-info/top_level.txt
aifoundry-0.1.0.dist-info/RECORD
