Metadata-Version: 2.4
Name: aifoundry
Version: 0.1.0
Summary: Enterprise-grade AI implementation tools with built-in compliance
Home-page: https://github.com/LOLA0786/Aifoundary
Author: AI Foundry Team
Author-email: your-email@example.com
Classifier: Development Status :: 3 - Alpha
Classifier: Intended Audience :: Developers
Classifier: Topic :: Scientific/Engineering :: Artificial Intelligence
Classifier: License :: OSI Approved :: MIT License
Classifier: Programming Language :: Python :: 3
Classifier: Programming Language :: Python :: 3.8
Requires-Python: >=3.8
Dynamic: author
Dynamic: author-email
Dynamic: classifier
Dynamic: description
Dynamic: description-content-type
Dynamic: home-page
Dynamic: requires-python
Dynamic: summary
